{
  "World_Cup": "70excpe1synn9kadnbppahdn7",
  "UEFA_Euros": "8tddm56zbasf57jkkay4kbf11",
  "CONCACAF_Gold_Cup": "f51991ex45qhp1p3iu74u4d4e",
  "Conference_League": "c7b8o53flg36wbuevfzy3lb10",
  "Championship": "7ntvbsyq31jnzoqoa8850b9b8",
  "FA_Cup": "2hj3286pqov1g1g59k2t2qcgm",
  "League_Cup": "725gd73msyt08xm76v7gkxj7u",
  "Primeira_Liga": "8yi6ejjd1zudcqtbn07haahg6",
  "Taca_da_Liga": "bqvy41un7sf86rbse9tv810x7",
  "Taca_de_Portugal": "5jd0k2txwnq69frs79eulba8j",
  "Eredivisie": "akmkihra9ruad09ljapsm84b3",
  "KNVB_Beker": "cbdbziaqczfuyuwqsylqi26zd",
  "Scottish_Premiership": "e21cf135btr8t3upw0vl6n6x0",
  "Scottish_Cup": "8kt53kt3mfo29gldhkl05u25b",
  "Scottish_League_Cup": "eog6knrkfei68si736fpquyzc",
  "Super_Lig": "482ofyysbdbeoxauk19yg7tdt",
  "Turkish_Cup": "7af85xa75vozt2l4hzi6ryts7",
  "Belgian_First_Division": "4zwgbb66rif2spcoeeol2motx",
  "Belgian_Cup": "1qt9bfl6dhydf4tpano6n1p7s",
  "Swiss_Super_League": "e0lck99w8meo9qoalfrxgo33o",
  "Schweizer_Pokal": "8cit3whr514nnd4zkaovsnqn",
  "Austrian_Bundesliga": "5c96g1zm7vo5ons9c42uy2w3r",
  "Austrian_Cup": "1ncmha8yglhyyhg6gtaujymqf",
  "Greek_Super_League": "c0r21rtokgnbtc0o2rldjmkxu",
  "Greek_Cup": "10x5pvhifwo4y7hs3fz9hf245",
  "Danish_Superliga": "29actv1ohj8r10kd9hu0jnb0n",
  "DBU_Pokalen": "8ztsv3pzrsyq5w1r3a0nfk1y5",
  "Eliteserien": "9ynnnx1qmkizq1o3qr3v0nsuk",
  "Allsvenskan": "b60nisd3qn427jm0hrg9kvmab",
  "Svenska_Cupen": "d9eaigzyfnfiraqc3ius757tl",
  "Ukrainian_Premier_League": "6wubmo7di3kdpflluf6s8c7vs",
  "Ukrainian_Cup": "2kuyfkulm5lsgjxynrgh3vz70",
  "Croatian_HNL": "1b70m6qtxrp75b4vtk8hxh8c3",
  "Croatian_Cup": "3z6xfyd3ovi5x09orlo4rmskx",
  "Czech_Liga": "bu1l7ckihyr0errxw61p0m05",
  "Czech_Cup": "193wqkyb0v5jnsblhvd2ocmyo",
  "Ekstraklasa": "7hl0svs2hg225i2zud0g3xzp2",
  "Polish_Cup": "b3ufcd24wfnnd5j98ped6irfu",
  "Romanian_Liga_I": "89ovpy1rarewwzqvi30bfdr8b",
  "Cupa_Romaniei": "65q4uwm6ol1rkf5dp89m8omny",
  "Serbian_Super_Liga": "3ww12jab49q8q8mk9avdwjqgk",
  "Serbian_Cup": "29lni33vxqrl1tqhadrnfid6t",
  "NB_I": "47s2kt0e8m444ftqvsrqa3bvq",
  "Magyar_Kupa": "chfah95whw2m0sbdq6cvfac7q",
  "Bulgarian_First_League": "c0yqkbilbbg70ij2473xymmqv",
  "Bulgarian_Cup": "22euhl6zy56cp651ipq99rooq",
  "Ligat_Haal": "2xg0qvif1rh7du6wmk2eleku3",
  "Israeli_Cup": "481owj46t50pkw9k6qz1c4jm6",
  "Veikkausliiga": "dvstmwnvw0mt5p38twn9yttyb",
  "Suomen_Cup": "6hlw7rhrpe9garwmfoxu4lebc",
  "Slovak_Liga": "1mpjd0vbxbtu9zw89yj09xk3z",
  "Slovak_Cup": "ahl3vljaignq9ebaos4uqkrvo",
  "Slovenian_Liga": "7nmz249q89qg5ezcvzlheljji",
  "Slovenian_Cup": "ggsjtgoapnah61wu939ni8js",
  "Azerbaijan_Premier": "3428tckxcirwwh3o3jgc1m8ji",
  "Azerbaijan_Cup": "9gvvndi7vk9fzvpe65pv5x2ir",
  "Kazakhstan_Premier": "9ikchyu9fb8bvx0s673jofj6s",
  "Irish_Premier": "4mbfidy8zum5u0aqjqo0vuqs2",
  "Bosnian_Premier": "4yngyfinzd6bb1k7anqtqs0wt",
  "Icelandic_Premier": "zilopfej2h0n3vpan5tcynpo",
  "Macedonian_First": "dl5v19e4466jn4fuufhlae7jm",
  "Kosovo_Superliga": "dwiqifdd70ytjytcs09vzosb3",
  "Maltese_Premier": "5taraea6mqjjldg9zxswo825y",
  "Gibraltar_Premier": "dzu6b07r25e3pk2uahxi5mzsz",
  "Armenian_Premier": "dn9kmfdbz74lzt3m8e9g0vwjq",
  "Cyprus_First": "btouq8t23agr62ij7e0ju5p6n",
  "Copa_del_Rey": "apdwh753fupxheygs8seahh7x",
  "Supercopa": "sd8z02fe455z2fjvlxvxh0zo",
  "Coupe_de_France": "3n9mk5b2mxmq831wfmv6pu86i",
  "Trophee_Champions": "1nsu863daf68kns4l7ou69orf",
  "DFB_Pokal": "486rhdgz7yc0sygziht7hje65",
  "Coppa_Italia": "6694fff47wqxl10lrd9tb91f8"
}